[
  {
    "v": "MIC 1 1",
    "r": [
      "2KI 15 32",
      "2CH 27 1",
      "ISA 1 1",
      "ISA 1 2",
      "ISA 7 9",
      "JER 26 18",
      "HOS 1 1",
      "HOS 4 15",
      "HOS 5 5",
      "HOS 6 10",
      "HOS 8 14",
      "HOS 12 1",
      "AMO 1 1",
      "AMO 2 4",
      "AMO 3 1",
      "AMO 6 1",
      "MIC 1 5",
      "MIC 1 14",
      "HAB 1 1"
    ]
  },
  {
    "v": "MIC 1 2",
    "r": [
      "DEU 32 1",
      "1KI 22 28",
      "PSA 11 4",
      "PSA 24 1",
      "PSA 28 2",
      "PSA 49 1",
      "PSA 49 2",
      "PSA 50 1",
      "PSA 50 7",
      "PSA 50 12",
      "PRO 8 4",
      "ISA 1 2",
      "JER 6 19",
      "JER 22 29",
      "JER 29 23",
      "JON 2 7",
      "JON 2 8",
      "MIC 6 1",
      "HAB 2 20",
      "MAL 2 14",
      "MAL 3 5",
      "MAR 7 14",
      "REV 2 7",
      "REV 2 11",
      "REV 2 17",
      "REV 2 29",
      "REV 3 6",
      "REV 3 13",
      "REV 3 22"
    ]
  },
  {
    "v": "MIC 1 3",
    "r": [
      "DEU 32 13",
      "DEU 33 29",
      "JOB 40 12",
      "PSA 115 3",
      "ISA 2 10",
      "ISA 25 10",
      "ISA 26 21",
      "ISA 63 3",
      "ISA 64 1",
      "EZE 3 12",
      "HOS 5 14",
      "AMO 4 13",
      "AMO 9 5",
      "HAB 3 19"
    ]
  },
  {
    "v": "MIC 1 4",
    "r": [
      "JDG 5 4",
      "PSA 68 2",
      "PSA 97 5",
      "ISA 64 1",
      "AMO 9 5",
      "NAH 1 5",
      "HAB 3 6",
      "HAB 3 10",
      "ZEC 14 4",
      "2PE 3 10",
      "REV 20 11"
    ]
  },
  {
    "v": "MIC 1 5",
    "r": [
      "1KI 11 7",
      "1KI 13 32",
      "1KI 16 24",
      "2KI 16 3",
      "2KI 16 10",
      "2KI 17 7",
      "2KI 17 23",
      "2CH 28 2",
      "2CH 28 4",
      "2CH 28 23",
      "2CH 36 14",
      "ISA 50 1",
      "ISA 59 1",
      "JER 2 17",
      "JER 2 19",
      "JER 4 18",
      "JER 5 25",
      "JER 6 19",
      "JER 23 13",
      "JER 23 14",
      "LAM 5 16",
      "EZE 16 46",
      "HOS 7 1",
      "HOS 8 5",
      "AMO 6 1",
      "AMO 8 14",
      "1TH 2 15"
    ]
  },
  {
    "v": "MIC 1 6",
    "r": [
      "2KI 18 9",
      "2KI 18 10",
      "2KI 19 25",
      "ISA 25 2",
      "ISA 25 12",
      "JER 9 11",
      "JER 51 25",
      "JER 51 37",
      "LAM 4 1",
      "EZE 13 14",
      "HOS 13 16",
      "AMO 5 11",
      "AMO 6 8",
      "MIC 3 12",
      "HAB 3 13",
      "MAT 24 2"
    ]
  },
  {
    "v": "MIC 1 7",
    "r": [
      "LEV 26 30",
      "DEU 9 21",
      "DEU 23 18",
      "2KI 23 14",
      "2CH 31 1",
      "2CH 34 6",
      "ISA 27 9",
      "JER 44 17",
      "EZE 6 6",
      "HOS 2 5",
      "HOS 2 12",
      "HOS 2 14",
      "HOS 8 5",
      "HOS 8 6",
      "HOS 10 5",
      "JOE 3 3",
      "REV 18 3",
      "REV 18 9",
      "REV 18 12"
    ]
  },
  {
    "v": "MIC 1 8",
    "r": [
      "2KI 18 13",
      "EST 4 1",
      "JOB 30 29",
      "PSA 102 6",
      "ISA 13 21",
      "ISA 16 9",
      "ISA 20 2",
      "ISA 21 3",
      "ISA 22 4",
      "JER 4 19",
      "JER 9 1",
      "JER 9 10",
      "JER 9 19",
      "JER 48 36"
    ]
  },
  {
    "v": "MIC 1 9",
    "r": [
      "2KI 18 9",
      "2KI 18 13",
      "2CH 32 1",
      "ISA 1 5",
      "ISA 3 26",
      "ISA 8 7",
      "ISA 10 28",
      "ISA 10 32",
      "ISA 36 1",
      "ISA 36 2",
      "ISA 37 22",
      "JER 15 18",
      "JER 30 11",
      "JER 30 12",
      "JER 30 15",
      "MIC 1 12"
    ]
  },
  {
    "v": "MIC 1 10",
    "r": [
      "JOS 18 23",
      "2SA 1 20",
      "JOB 2 8",
      "JER 6 26",
      "LAM 3 29",
      "AMO 5 13",
      "AMO 6 10"
    ]
  },
  {
    "v": "MIC 1 11",
    "r": [
      "ISA 16 2",
      "ISA 20 4",
      "ISA 47 2",
      "JER 13 22",
      "JER 48 6",
      "JER 48 9",
      "EZE 16 37",
      "EZE 23 29",
      "MIC 1 8",
      "NAH 3 5",
      "ZEC 14 5"
    ]
  },
  {
    "v": "MIC 1 12",
    "r": [
      "RUT 1 20",
      "1SA 4 13",
      "JOB 30 26",
      "ISA 45 7",
      "ISA 59 9",
      "JER 8 15",
      "JER 14 19",
      "AMO 3 6",
      "MIC 1 9"
    ]
  },
  {
    "v": "MIC 1 13",
    "r": [
      "GEN 19 17",
      "EXO 32 21",
      "JOS 10 3",
      "JOS 15 39",
      "1KI 13 33",
      "1KI 14 16",
      "1KI 16 31",
      "2KI 8 18",
      "2KI 16 3",
      "2KI 18 13",
      "2KI 18 17",
      "2CH 11 9",
      "2CH 32 9",
      "JOB 39 10",
      "ISA 10 31",
      "ISA 37 8",
      "JER 3 8",
      "JER 4 29",
      "JER 34 7",
      "EZE 23 11",
      "MIC 1 5",
      "REV 2 14",
      "REV 2 20",
      "REV 18 1"
    ]
  },
  {
    "v": "MIC 1 14",
    "r": [
      "JOS 15 44",
      "2SA 8 2",
      "2KI 16 8",
      "2KI 18 14",
      "2CH 16 1",
      "PSA 62 9",
      "PSA 118 8",
      "PSA 146 3",
      "ISA 30 6",
      "JER 15 18"
    ]
  },
  {
    "v": "MIC 1 15",
    "r": [
      "GEN 38 1",
      "JOS 12 15",
      "JOS 15 35",
      "JOS 15 44",
      "1SA 22 1",
      "2CH 11 7",
      "ISA 7 17",
      "ISA 10 3",
      "ISA 10 5",
      "JER 49 1"
    ]
  },
  {
    "v": "MIC 1 16",
    "r": [
      "DEU 28 41",
      "DEU 28 56",
      "2KI 17 6",
      "JOB 1 20",
      "ISA 3 16",
      "ISA 15 2",
      "ISA 22 12",
      "ISA 39 6",
      "JER 4 8",
      "JER 6 26",
      "JER 7 29",
      "JER 16 6",
      "LAM 2 19",
      "LAM 4 5",
      "AMO 8 10"
    ]
  },
  {
    "v": "MIC 2 1",
    "r": [
      "GEN 31 29",
      "DEU 28 32",
      "1KI 21 7",
      "EST 3 8",
      "EST 5 14",
      "EST 9 25",
      "JOB 15 35",
      "PSA 7 14",
      "PSA 36 4",
      "PSA 36 5",
      "PSA 58 3",
      "PSA 140 1",
      "PRO 3 27",
      "PRO 4 16",
      "PRO 6 12",
      "PRO 6 14",
      "PRO 12 2",
      "ISA 3 14",
      "ISA 5 8",
      "ISA 29 20",
      "ISA 32 7",
      "ISA 59 3",
      "JER 18 18",
      "EZE 11 2",
      "HOS 7 6",
      "MIC 6 12",
      "NAH 1 11",
      "ZEC 7 10",
      "MAT 27 1",
      "MAR 15 1",
      "LUK 20 19",
      "LUK 22 2",
      "JOH 19 11",
      "ACT 23 12",
      "ACT 23 15",
      "ROM 1 30"
    ]
  },
  {
    "v": "MIC 2 2",
    "r": [
      "EXO 20 17",
      "EXO 22 21",
      "1SA 12 3",
      "1KI 21 2",
      "1KI 21 7",
      "2KI 9 26",
      "NEH 5 1",
      "JOB 24 2",
      "JOB 31 38",
      "ISA 3 14",
      "ISA 5 8",
      "JER 22 17",
      "EZE 18 12",
      "EZE 22 12",
      "EZE 45 9",
      "AMO 4 1",
      "AMO 8 4",
      "MIC 3 9",
      "MIC 6 12",
      "HAB 2 5",
      "MAL 3 5",
      "MAT 23 13",
      "1TI 6 10"
    ]
  },
  {
    "v": "MIC 2 3",
    "r": [
      "ISA 2 11",
      "ISA 3 16",
      "ISA 5 19",
      "ISA 28 14",
      "ISA 29 20",
      "JER 8 3",
      "JER 13 15",
      "JER 18 11",
      "JER 27 12",
      "JER 34 17",
      "JER 36 23",
      "JER 43 2",
      "LAM 1 14",
      "LAM 2 17",
      "LAM 5 5",
      "DAN 4 37",
      "DAN 5 20",
      "AMO 2 14",
      "AMO 5 13",
      "AMO 9 1",
      "MIC 2 1",
      "ZEP 1 17",
      "ROM 16 4",
      "EPH 5 16",
      "JAM 2 13"
    ]
  },
  {
    "v": "MIC 2 4",
    "r": [
      "NUM 23 7",
      "NUM 23 18",
      "NUM 24 3",
      "NUM 24 15",
      "DEU 28 29",
      "2SA 1 17",
      "2KI 17 23",
      "2CH 35 25",
      "2CH 36 20",
      "JOB 27 1",
      "ISA 6 11",
      "ISA 14 4",
      "ISA 24 3",
      "ISA 63 17",
      "JER 4 13",
      "JER 9 10",
      "JER 9 16",
      "JER 9 17",
      "JER 14 18",
      "JER 25 9",
      "LAM 1 1",
      "EZE 2 10",
      "EZE 16 44",
      "JOE 1 8",
      "JOE 1 13",
      "AMO 5 1",
      "AMO 5 17",
      "MIC 1 15",
      "MIC 2 10",
      "HAB 2 6",
      "ZEP 1 2",
      "MAR 12 12"
    ]
  },
  {
    "v": "MIC 2 5",
    "r": [
      "DEU 23 2",
      "DEU 23 8",
      "DEU 32 8",
      "JOS 18 4",
      "JOS 18 10",
      "2KI 17 23",
      "1CH 16 18",
      "NEH 7 61",
      "PSA 16 6",
      "HOS 9 3"
    ]
  },
  {
    "v": "MIC 2 6",
    "r": [
      "PSA 74 9",
      "ISA 30 10",
      "JER 6 14",
      "JER 8 11",
      "JER 26 8",
      "JER 26 20",
      "EZE 3 26",
      "EZE 20 46",
      "EZE 21 2",
      "AMO 2 12",
      "AMO 7 13",
      "AMO 8 11",
      "MIC 6 16",
      "ACT 4 17",
      "ACT 5 28",
      "ACT 5 40",
      "ACT 7 51",
      "1TH 2 15"
    ]
  },
  {
    "v": "MIC 2 7",
    "r": [
      "NUM 11 23",
      "PSA 15 2",
      "PSA 18 26",
      "PSA 19 7",
      "PSA 84 11",
      "PSA 119 65",
      "PSA 119 70",
      "PSA 119 92",
      "PSA 119 99",
      "PRO 2 7",
      "PRO 10 9",
      "PRO 10 29",
      "PRO 14 2",
      "PRO 28 18",
      "ISA 48 1",
      "ISA 50 2",
      "ISA 58 1",
      "ISA 59 1",
      "JER 2 4",
      "JER 15 16",
      "HOS 14 9",
      "MIC 3 9",
      "ZEC 4 6",
      "MAT 3 8",
      "JOH 8 39",
      "ROM 2 28",
      "ROM 7 13",
      "ROM 9 6",
      "2CO 6 12",
      "2TI 3 5"
    ]
  },
  {
    "v": "MIC 2 8",
    "r": [
      "2SA 20 19",
      "2CH 28 5",
      "PSA 55 20",
      "PSA 120 6",
      "ISA 9 21"
    ]
  },
  {
    "v": "MIC 2 9",
    "r": [
      "1SA 26 19",
      "PSA 72 19",
      "JER 10 20",
      "EZE 39 21",
      "JOE 3 6",
      "MIC 2 2",
      "HAB 2 14",
      "ZEC 2 5",
      "MAT 23 13",
      "MAR 12 40",
      "LUK 20 47",
      "2CO 3 18",
      "2CO 4 6"
    ]
  },
  {
    "v": "MIC 2 10",
    "r": [
      "LEV 18 24",
      "LEV 20 22",
      "DEU 4 26",
      "DEU 12 9",
      "DEU 30 18",
      "JOS 23 15",
      "1KI 9 7",
      "2KI 15 29",
      "2KI 17 6",
      "2CH 7 20",
      "2CH 36 20",
      "PSA 95 11",
      "PSA 106 38",
      "JER 3 2",
      "JER 9 19",
      "JER 10 18",
      "EZE 36 12",
      "EZE 36 17",
      "EZE 36 19",
      "HEB 4 1"
    ]
  },
  {
    "v": "MIC 2 11",
    "r": [
      "1KI 13 18",
      "1KI 22 6",
      "1KI 22 21",
      "2CH 18 19",
      "ISA 9 15",
      "ISA 30 10",
      "JER 5 31",
      "JER 6 13",
      "JER 8 10",
      "JER 14 14",
      "JER 23 14",
      "JER 23 17",
      "JER 23 25",
      "JER 23 32",
      "JER 27 14",
      "JER 28 2",
      "JER 28 15",
      "JER 29 21",
      "LAM 2 14",
      "EZE 13 3",
      "EZE 13 22",
      "MIC 3 5",
      "MIC 3 11",
      "ROM 16 18",
      "2CO 11 13",
      "PHP 3 19",
      "2TH 2 8",
      "2PE 2 1",
      "2PE 2 13",
      "1JO 4 1",
      "REV 16 13"
    ]
  },
  {
    "v": "MIC 2 12",
    "r": [
      "GEN 36 33",
      "1CH 1 44",
      "ISA 11 11",
      "ISA 27 12",
      "ISA 34 6",
      "JER 3 18",
      "JER 23 3",
      "JER 31 7",
      "EZE 34 11",
      "EZE 34 13",
      "EZE 34 22",
      "EZE 34 31",
      "EZE 36 37",
      "EZE 37 21",
      "HOS 1 11",
      "AMO 1 12",
      "MIC 4 6",
      "MIC 4 7",
      "MIC 5 7",
      "MIC 7 14",
      "MIC 7 18",
      "ZEP 3 20",
      "ZEC 8 22",
      "ZEC 9 14",
      "ZEC 10 6",
      "ZEC 10 8"
    ]
  },
  {
    "v": "MIC 2 13",
    "r": [
      "EXO 14 19",
      "JOS 3 6",
      "ISA 42 7",
      "ISA 42 13",
      "ISA 45 1",
      "ISA 49 9",
      "ISA 49 24",
      "ISA 51 9",
      "ISA 51 12",
      "ISA 52 12",
      "ISA 55 4",
      "ISA 59 16",
      "JER 23 5",
      "JER 51 20",
      "EZE 34 23",
      "DAN 2 34",
      "DAN 2 44",
      "HOS 1 11",
      "HOS 2 2",
      "HOS 3 5",
      "HOS 13 14",
      "MIC 4 7",
      "ZEC 9 14",
      "ZEC 10 5",
      "ZEC 10 12",
      "ZEC 12 3",
      "JOH 10 27",
      "1CO 15 21",
      "HEB 2 9",
      "HEB 2 14",
      "HEB 6 20",
      "REV 7 17",
      "REV 17 14",
      "REV 19 13"
    ]
  },
  {
    "v": "MIC 3 1",
    "r": [
      "DEU 1 13",
      "DEU 16 18",
      "2CH 19 5",
      "NEH 13 17",
      "PSA 14 4",
      "PSA 82 1",
      "ISA 1 10",
      "ISA 10 2",
      "JER 5 4",
      "JER 5 5",
      "JER 13 15",
      "JER 22 2",
      "EZE 22 6",
      "EZE 34 3",
      "HOS 5 1",
      "AMO 4 1",
      "AMO 6 1",
      "MIC 3 9",
      "1CO 6 5"
    ]
  },
  {
    "v": "MIC 3 2",
    "r": [
      "1KI 21 20",
      "1KI 22 6",
      "2CH 19 2",
      "PSA 15 4",
      "PSA 53 4",
      "PSA 139 21",
      "PRO 28 4",
      "ISA 3 15",
      "ISA 5 20",
      "EZE 22 27",
      "EZE 34 3",
      "AMO 4 1",
      "AMO 5 10",
      "AMO 5 15",
      "AMO 8 4",
      "ZEP 3 3",
      "ZEC 11 4",
      "LUK 19 14",
      "JOH 7 7",
      "JOH 15 18",
      "JOH 15 23",
      "JOH 18 40",
      "ACT 7 51",
      "ROM 1 32",
      "ROM 12 9",
      "2TI 3 3"
    ]
  },
  {
    "v": "MIC 3 3",
    "r": [
      "PSA 14 4",
      "PRO 30 14",
      "ISA 3 15",
      "EZE 11 3",
      "EZE 11 6",
      "AMO 8 4",
      "ZEP 3 3"
    ]
  },
  {
    "v": "MIC 3 4",
    "r": [
      "DEU 31 17",
      "DEU 32 19",
      "1SA 8 18",
      "JOB 27 9",
      "PSA 18 41",
      "PRO 1 28",
      "PRO 28 9",
      "ISA 1 15",
      "ISA 3 11",
      "ISA 59 1",
      "ISA 59 3",
      "JER 2 27",
      "JER 5 31",
      "JER 14 12",
      "JER 33 5",
      "EZE 8 18",
      "MIC 2 3",
      "ZEC 7 13",
      "MAT 7 22",
      "LUK 13 25",
      "JOH 9 31",
      "ROM 2 8",
      "JAM 2 13"
    ]
  },
  {
    "v": "MIC 3 5",
    "r": [
      "PRO 28 21",
      "ISA 3 12",
      "ISA 9 15",
      "ISA 56 9",
      "JER 6 4",
      "JER 6 14",
      "JER 14 14",
      "JER 23 9",
      "JER 23 27",
      "JER 23 32",
      "JER 28 15",
      "JER 29 21",
      "LAM 2 14",
      "EZE 13 9",
      "EZE 13 10",
      "EZE 13 18",
      "EZE 13 19",
      "EZE 22 25",
      "HOS 4 5",
      "MIC 2 11",
      "MIC 3 11",
      "MAL 2 8",
      "MAT 7 15",
      "MAT 15 14",
      "ROM 16 18"
    ]
  },
  {
    "v": "MIC 3 6",
    "r": [
      "PSA 74 9",
      "ISA 8 20",
      "ISA 29 10",
      "ISA 59 10",
      "JER 13 16",
      "JER 15 9",
      "JER 18 18",
      "EZE 7 26",
      "EZE 13 9",
      "EZE 13 22",
      "EZE 13 23",
      "AMO 8 9",
      "ZEC 13 2"
    ]
  },
  {
    "v": "MIC 3 7",
    "r": [
      "EXO 8 18",
      "EXO 9 11",
      "LEV 13 45",
      "1SA 9 9",
      "1SA 14 37",
      "1SA 28 6",
      "1SA 28 15",
      "PSA 74 9",
      "ISA 44 25",
      "ISA 47 12",
      "JER 18 18",
      "EZE 24 17",
      "EZE 24 22",
      "DAN 2 9",
      "AMO 8 11",
      "MIC 7 16",
      "ZEC 13 4",
      "2TI 3 8"
    ]
  },
  {
    "v": "MIC 3 8",
    "r": [
      "JOB 32 18",
      "ISA 11 2",
      "ISA 58 1",
      "JER 1 18",
      "JER 6 11",
      "JER 15 19",
      "JER 20 9",
      "EZE 3 14",
      "EZE 16 2",
      "EZE 20 4",
      "EZE 22 2",
      "EZE 23 36",
      "EZE 43 10",
      "MAT 3 7",
      "MAT 7 29",
      "MAR 3 17",
      "ACT 4 8",
      "ACT 4 19",
      "ACT 7 51",
      "ACT 7 54",
      "ACT 13 9",
      "ACT 18 5",
      "ACT 18 9",
      "1CO 2 4",
      "1CO 2 12"
    ]
  },
  {
    "v": "MIC 3 9",
    "r": [
      "EXO 3 16",
      "LEV 26 15",
      "DEU 27 19",
      "NEH 13 17",
      "PSA 58 1",
      "PRO 17 15",
      "PRO 17 23",
      "ISA 1 23",
      "JER 5 28",
      "HOS 5 1",
      "AMO 5 7",
      "MIC 3 1"
    ]
  },
  {
    "v": "MIC 3 10",
    "r": [
      "JER 22 13",
      "EZE 22 3",
      "EZE 22 25",
      "HAB 2 9",
      "ZEP 3 3",
      "MAT 27 25",
      "JOH 11 50"
    ]
  },
  {
    "v": "MIC 3 11",
    "r": [
      "NUM 16 15",
      "NUM 22 7",
      "1SA 4 3",
      "1SA 8 3",
      "1SA 12 3",
      "PRO 17 23",
      "ISA 1 23",
      "ISA 48 2",
      "ISA 56 11",
      "JER 5 12",
      "JER 6 13",
      "JER 7 4",
      "JER 7 8",
      "JER 8 10",
      "JER 23 17",
      "EZE 22 12",
      "EZE 22 27",
      "HOS 4 18",
      "AMO 5 14",
      "AMO 9 10",
      "MIC 3 5",
      "MIC 7 3",
      "ZEP 3 3",
      "ZEP 3 4",
      "MAL 1 10",
      "MAL 2 9",
      "MAT 3 9",
      "ACT 8 18",
      "ROM 2 17",
      "1TI 3 3",
      "TIT 1 11",
      "1PE 5 2",
      "2PE 2 1",
      "2PE 2 14",
      "JDE 1 11"
    ]
  },
  {
    "v": "MIC 3 12",
    "r": [
      "PSA 79 1",
      "PSA 107 34",
      "ISA 2 2",
      "ISA 32 14",
      "JER 9 10",
      "JER 22 5",
      "JER 26 18",
      "MIC 1 6",
      "MIC 4 1",
      "MAT 24 2",
      "ACT 6 13"
    ]
  },
  {
    "v": "MIC 4 1",
    "r": [
      "GEN 49 1",
      "GEN 49 10",
      "PSA 22 27",
      "PSA 68 15",
      "PSA 68 29",
      "PSA 72 7",
      "PSA 72 16",
      "PSA 86 9",
      "PSA 110 3",
      "ISA 2 1",
      "ISA 2 2",
      "ISA 11 9",
      "ISA 27 13",
      "ISA 43 6",
      "ISA 49 6",
      "ISA 49 19",
      "ISA 54 2",
      "ISA 60 3",
      "ISA 60 7",
      "ISA 66 18",
      "JER 3 17",
      "JER 16 19",
      "JER 48 47",
      "EZE 17 22",
      "EZE 17 23",
      "EZE 38 16",
      "EZE 40 2",
      "EZE 43 12",
      "DAN 2 28",
      "DAN 2 35",
      "DAN 2 44",
      "DAN 7 14",
      "DAN 7 18",
      "DAN 7 22",
      "DAN 7 27",
      "DAN 10 14",
      "HOS 3 5",
      "MIC 3 12",
      "ZEP 3 9",
      "ZEC 2 11",
      "ZEC 8 3",
      "ZEC 14 10",
      "ZEC 14 16",
      "MAL 1 11",
      "ACT 2 17",
      "ROM 11 25",
      "HEB 1 2",
      "2PE 3 3",
      "REV 11 15",
      "REV 15 4",
      "REV 20 4",
      "REV 21 1"
    ]
  },
  {
    "v": "MIC 4 2",
    "r": [
      "DEU 6 1",
      "PSA 25 8",
      "PSA 25 12",
      "PSA 110 2",
      "ISA 2 3",
      "ISA 42 1",
      "ISA 51 4",
      "ISA 54 13",
      "JER 31 6",
      "JER 50 4",
      "HOS 6 3",
      "ZEC 2 11",
      "ZEC 8 20",
      "ZEC 8 22",
      "ZEC 14 8",
      "ZEC 14 16",
      "MAT 11 25",
      "MAT 28 19",
      "MAR 16 15",
      "MAR 16 20",
      "LUK 24 47",
      "JOH 6 45",
      "JOH 7 17",
      "ACT 1 8",
      "ACT 10 32",
      "ACT 13 42",
      "ACT 13 46",
      "ROM 10 12",
      "ROM 15 19",
      "JAM 1 19"
    ]
  },
  {
    "v": "MIC 4 3",
    "r": [
      "1SA 2 10",
      "PSA 2 5",
      "PSA 46 9",
      "PSA 46 10",
      "PSA 68 30",
      "PSA 72 7",
      "PSA 82 8",
      "PSA 96 13",
      "PSA 98 9",
      "PSA 110 1",
      "PSA 110 5",
      "ISA 2 4",
      "ISA 9 7",
      "ISA 11 3",
      "ISA 25 3",
      "ISA 51 5",
      "ISA 60 12",
      "ISA 60 17",
      "ISA 65 25",
      "DAN 2 44",
      "HOS 2 18",
      "HOS 2 20",
      "JOE 3 2",
      "JOE 3 9",
      "MIC 5 15",
      "MIC 7 16",
      "ZEC 9 10",
      "ZEC 12 3",
      "ZEC 14 3",
      "ZEC 14 12",
      "MAT 25 31",
      "JOH 5 22",
      "JOH 5 27",
      "JOH 16 8",
      "ACT 17 31",
      "REV 19 11",
      "REV 19 17",
      "REV 20 8"
    ]
  },
  {
    "v": "MIC 4 4",
    "r": [
      "LEV 26 6",
      "1KI 4 25",
      "1KI 5 5",
      "PRO 3 25",
      "ISA 1 20",
      "ISA 26 16",
      "ISA 32 17",
      "ISA 40 5",
      "ISA 54 14",
      "ISA 58 14",
      "JER 23 4",
      "JER 23 5",
      "JER 30 10",
      "EZE 34 25",
      "EZE 34 28",
      "EZE 38 11",
      "EZE 39 26",
      "MIC 5 3",
      "ZEP 3 13",
      "ZEC 3 10"
    ]
  },
  {
    "v": "MIC 4 5",
    "r": [
      "GEN 17 1",
      "EXO 3 14",
      "DEU 27 10",
      "JOS 24 15",
      "2KI 17 29",
      "2KI 17 34",
      "PSA 20 6",
      "PSA 48 14",
      "PSA 71 16",
      "PSA 145 1",
      "ISA 2 5",
      "ISA 26 8",
      "JER 2 10",
      "JER 32 40",
      "ZEC 10 12",
      "COL 2 6",
      "COL 3 17"
    ]
  },
  {
    "v": "MIC 4 6",
    "r": [
      "PSA 38 17",
      "PSA 147 2",
      "ISA 35 3",
      "ISA 56 8",
      "JER 3 18",
      "JER 30 17",
      "JER 31 8",
      "EZE 34 12",
      "EZE 34 16",
      "EZE 36 24",
      "EZE 37 21",
      "EZE 39 25",
      "MIC 2 12",
      "ZEP 3 19",
      "LUK 19 10",
      "JOH 10 16",
      "HEB 12 12"
    ]
  },
  {
    "v": "MIC 4 7",
    "r": [
      "PSA 2 6",
      "ISA 6 13",
      "ISA 9 6",
      "ISA 10 21",
      "ISA 11 11",
      "ISA 24 23",
      "ISA 49 21",
      "ISA 60 22",
      "ISA 66 8",
      "EZE 43 7",
      "DAN 7 14",
      "DAN 7 27",
      "HOS 1 10",
      "JOE 3 17",
      "OBA 1 21",
      "MIC 2 12",
      "MIC 2 13",
      "MIC 5 3",
      "MIC 5 7",
      "MIC 7 18",
      "ZEP 3 20",
      "ZEC 9 13",
      "ZEC 10 5",
      "LUK 1 33",
      "ROM 11 5",
      "ROM 11 25",
      "REV 11 15"
    ]
  },
  {
    "v": "MIC 4 8",
    "r": [
      "GEN 35 21",
      "NUM 24 19",
      "2SA 5 7",
      "NEH 3 25",
      "PSA 24 7",
      "PSA 48 12",
      "SOS 4 4",
      "ISA 1 26",
      "ISA 5 2",
      "ISA 10 32",
      "DAN 2 44",
      "DAN 7 18",
      "OBA 1 21",
      "ZEC 9 9",
      "ZEC 9 10",
      "ZEC 9 12",
      "MAT 21 33",
      "MAR 12 1",
      "EPH 1 21",
      "REV 22 5"
    ]
  },
  {
    "v": "MIC 4 9",
    "r": [
      "ISA 3 1",
      "ISA 13 8",
      "ISA 21 3",
      "ISA 26 17",
      "JER 4 21",
      "JER 4 31",
      "JER 8 19",
      "JER 22 23",
      "JER 30 6",
      "JER 30 7",
      "JER 30 10",
      "JER 50 43",
      "LAM 4 20",
      "HOS 3 4",
      "HOS 10 3",
      "HOS 13 10"
    ]
  },
  {
    "v": "MIC 4 10",
    "r": [
      "2KI 20 18",
      "2KI 25 4",
      "2CH 33 11",
      "2CH 36 20",
      "2CH 36 23",
      "EZR 1 1",
      "PSA 106 10",
      "ISA 43 14",
      "ISA 45 13",
      "ISA 48 20",
      "ISA 52 9",
      "ISA 66 7",
      "JER 4 31",
      "JER 13 4",
      "JER 15 21",
      "HOS 1 10",
      "HOS 2 14",
      "HOS 13 13",
      "MIC 5 2",
      "MIC 7 8",
      "ZEC 2 7",
      "JOH 16 20",
      "REV 12 14"
    ]
  },
  {
    "v": "MIC 4 11",
    "r": [
      "PSA 83 5",
      "ISA 5 25",
      "ISA 8 7",
      "JER 52 4",
      "LAM 2 15",
      "LAM 2 16",
      "EZE 38 17",
      "JOE 3 2",
      "OBA 1 12",
      "MIC 7 10",
      "ZEC 12 3"
    ]
  },
  {
    "v": "MIC 4 12",
    "r": [
      "ISA 10 7",
      "ISA 21 10",
      "ISA 55 8",
      "JER 29 11",
      "JER 51 33",
      "JOE 3 12",
      "ZEC 14 1",
      "LUK 3 17",
      "ROM 11 33",
      "REV 14 14"
    ]
  },
  {
    "v": "MIC 4 13",
    "r": [
      "DEU 33 25",
      "JOS 6 19",
      "2SA 8 10",
      "2SA 8 11",
      "PSA 24 1",
      "PSA 68 29",
      "PSA 72 10",
      "ISA 5 28",
      "ISA 18 7",
      "ISA 23 18",
      "ISA 41 15",
      "ISA 60 6",
      "JER 51 33",
      "DAN 2 44",
      "MIC 5 7",
      "MIC 5 8",
      "ZEC 4 14",
      "ZEC 6 5",
      "ZEC 9 13",
      "ZEC 12 3",
      "ZEC 12 6",
      "ROM 15 25",
      "1CO 16 2",
      "REV 2 26",
      "REV 21 24"
    ]
  },
  {
    "v": "MIC 5 1",
    "r": [
      "GEN 35 19",
      "GEN 49 10",
      "DEU 28 49",
      "DEU 28 51",
      "DEU 33 27",
      "JDG 17 7",
      "1SA 8 5",
      "1KI 22 24",
      "2KI 24 2",
      "2KI 25 1",
      "JOB 16 10",
      "PRO 8 23",
      "ISA 8 9",
      "ISA 9 5",
      "ISA 10 6",
      "ISA 33 22",
      "JER 4 7",
      "JER 25 9",
      "LAM 3 30",
      "EZE 21 21",
      "EZE 21 32",
      "EZE 24 2",
      "DAN 9 25",
      "JOE 3 9",
      "AMO 2 3",
      "HAB 1 6",
      "HAB 3 16",
      "MAT 5 39",
      "MAT 26 67",
      "MAT 27 30",
      "LUK 19 43",
      "JOH 18 22",
      "JOH 19 3",
      "ACT 23 2",
      "2CO 11 20"
    ]
  },
  {
    "v": "MIC 5 2",
    "r": [
      "GEN 35 19",
      "GEN 48 7",
      "GEN 49 10",
      "EXO 18 21",
      "EXO 18 25",
      "DEU 1 15",
      "JDG 17 7",
      "RUT 4 11",
      "1SA 8 12",
      "1SA 10 19",
      "1SA 17 12",
      "1SA 17 18",
      "1SA 23 23",
      "1CH 2 50",
      "1CH 2 54",
      "1CH 4 4",
      "1CH 5 2",
      "PSA 90 2",
      "PSA 102 25",
      "PSA 132 6",
      "PRO 8 22",
      "ISA 7 14",
      "ISA 9 6",
      "ISA 11 1",
      "ISA 53 2",
      "JER 13 5",
      "JER 30 21",
      "EZE 17 22",
      "EZE 34 23",
      "EZE 37 22",
      "AMO 9 11",
      "MIC 4 10",
      "ZEC 9 9",
      "MAT 2 6",
      "MAT 28 18",
      "LUK 1 31",
      "LUK 2 4",
      "LUK 23 2",
      "LUK 23 38",
      "JOH 1 1",
      "JOH 7 42",
      "JOH 19 14",
      "1CO 1 27",
      "COL 1 17",
      "HEB 7 14",
      "HEB 13 8",
      "1JO 1 1",
      "REV 1 11",
      "REV 2 8",
      "REV 19 16",
      "REV 21 6"
    ]
  },
  {
    "v": "MIC 5 3",
    "r": [
      "1KI 14 16",
      "2CH 30 7",
      "PSA 67 3",
      "ISA 10 20",
      "ISA 11 11",
      "ISA 49 6",
      "ISA 66 7",
      "JER 23 5",
      "JER 31 1",
      "JER 31 7",
      "EZE 34 16",
      "HOS 2 9",
      "HOS 2 14",
      "HOS 11 8",
      "MIC 4 4",
      "MIC 4 7",
      "MIC 4 9",
      "MIC 6 14",
      "MIC 7 13",
      "ZEC 10 6",
      "MAT 1 21",
      "MAT 12 50",
      "MAT 25 40",
      "ROM 8 29",
      "ROM 9 27",
      "ROM 11 4",
      "HEB 1 11",
      "REV 12 1"
    ]
  },
  {
    "v": "MIC 5 4",
    "r": [
      "EXO 23 21",
      "1CH 29 11",
      "PSA 22 27",
      "PSA 23 1",
      "PSA 45 3",
      "PSA 72 8",
      "PSA 72 19",
      "PSA 93 1",
      "PSA 98 3",
      "PSA 145 12",
      "ISA 8 7",
      "ISA 40 10",
      "ISA 49 5",
      "ISA 49 9",
      "ISA 52 10",
      "ISA 52 13",
      "EZE 34 13",
      "EZE 34 22",
      "MIC 7 14",
      "ZEC 9 10",
      "MAT 2 6",
      "MAT 16 18",
      "MAT 25 31",
      "LUK 1 32",
      "JOH 5 22",
      "JOH 10 27",
      "JOH 10 38",
      "JOH 14 9",
      "JOH 20 17",
      "EPH 1 3",
      "1PE 1 5",
      "JDE 1 1",
      "REV 1 13",
      "REV 11 15"
    ]
  },
  {
    "v": "MIC 5 5",
    "r": [
      "JOB 5 19",
      "PSA 72 7",
      "PRO 6 16",
      "PRO 30 18",
      "PRO 30 29",
      "ECC 11 2",
      "ISA 7 14",
      "ISA 8 7",
      "ISA 9 6",
      "ISA 10 24",
      "ISA 14 25",
      "ISA 37 31",
      "ISA 44 28",
      "ISA 59 19",
      "ISA 65 8",
      "JER 33 15",
      "AMO 1 3",
      "AMO 1 6",
      "ZEC 1 18",
      "ZEC 9 10",
      "ZEC 9 13",
      "ZEC 10 3",
      "ZEC 10 11",
      "ZEC 12 6",
      "LUK 2 14",
      "JOH 14 27",
      "JOH 16 33",
      "EPH 2 14",
      "COL 1 20",
      "REV 17 14",
      "REV 19 14"
    ]
  },
  {
    "v": "MIC 5 6",
    "r": [
      "GEN 10 8",
      "DEU 32 2",
      "2KI 15 29",
      "2KI 17 3",
      "2KI 18 9",
      "2KI 19 32",
      "1CH 1 10",
      "2CH 33 11",
      "JOB 29 22",
      "PSA 72 6",
      "PSA 110 3",
      "ISA 6 13",
      "ISA 10 5",
      "ISA 14 2",
      "ISA 14 25",
      "ISA 33 1",
      "JER 14 22",
      "NAH 2 11",
      "ZEP 2 13",
      "ZEP 3 12",
      "LUK 1 71",
      "LUK 1 74"
    ]
  },
  {
    "v": "MIC 5 7",
    "r": [
      "DEU 32 2",
      "JDG 6 36",
      "PSA 72 6",
      "PSA 110 3",
      "ISA 32 15",
      "ISA 44 3",
      "ISA 55 10",
      "ISA 66 19",
      "JER 14 22",
      "EZE 5 5",
      "EZE 14 22",
      "EZE 47 1",
      "HOS 6 3",
      "HOS 14 5",
      "JOE 2 32",
      "AMO 5 15",
      "MIC 2 12",
      "MIC 4 13",
      "MIC 5 3",
      "MIC 5 8",
      "ZEP 3 13",
      "ZEC 9 13",
      "ZEC 14 8",
      "MAT 28 19",
      "ACT 9 15",
      "ACT 11 15",
      "ACT 13 46",
      "ACT 16 9",
      "ROM 9 30",
      "ROM 10 20",
      "ROM 11 5",
      "ROM 11 12",
      "ROM 15 19",
      "1CO 3 6"
    ]
  },
  {
    "v": "MIC 5 8",
    "r": [
      "GEN 49 9",
      "PSA 2 8",
      "PSA 2 9",
      "PSA 50 22",
      "PSA 110 5",
      "ISA 41 15",
      "HOS 5 14",
      "OBA 1 18",
      "MIC 4 13",
      "ZEC 9 15",
      "ZEC 10 5",
      "ZEC 12 3",
      "ZEC 14 18",
      "MAT 10 14",
      "ACT 18 6",
      "2CO 2 15",
      "HEB 2 3",
      "HEB 12 25"
    ]
  },
  {
    "v": "MIC 5 9",
    "r": [
      "PSA 10 12",
      "PSA 21 8",
      "PSA 106 26",
      "ISA 1 25",
      "ISA 11 14",
      "ISA 14 2",
      "ISA 26 11",
      "ISA 33 10",
      "ISA 37 36",
      "HAG 2 22",
      "ZEC 9 10",
      "LUK 19 27",
      "1CO 15 25",
      "REV 19 13",
      "REV 20 8"
    ]
  },
  {
    "v": "MIC 5 10",
    "r": [
      "PSA 20 7",
      "PSA 33 16",
      "ISA 2 7",
      "JER 3 23",
      "HOS 1 7",
      "HOS 14 3",
      "ZEC 9 10"
    ]
  },
  {
    "v": "MIC 5 11",
    "r": [
      "ISA 2 6",
      "ISA 2 12",
      "ISA 6 11",
      "ISA 27 9",
      "EZE 38 11",
      "HOS 10 14",
      "AMO 5 9",
      "ZEC 4 6"
    ]
  },
  {
    "v": "MIC 5 12",
    "r": [
      "DEU 18 10",
      "ISA 2 6",
      "ISA 2 8",
      "ISA 2 18",
      "ISA 2 20",
      "ISA 8 19",
      "ISA 27 9",
      "ISA 44 17",
      "EZE 16 41",
      "EZE 36 25",
      "ZEC 13 1",
      "ZEC 13 2",
      "REV 19 20",
      "REV 22 15"
    ]
  },
  {
    "v": "MIC 5 13",
    "r": [
      "ISA 2 8",
      "ISA 17 7",
      "ISA 27 9",
      "EZE 6 9",
      "EZE 16 41",
      "EZE 36 25",
      "EZE 37 23",
      "HOS 2 16",
      "HOS 14 3",
      "HOS 14 8",
      "ZEC 13 2"
    ]
  },
  {
    "v": "MIC 5 14",
    "r": [
      "EXO 34 13",
      "PSA 149 7",
      "PSA 149 9",
      "JER 12 17"
    ]
  },
  {
    "v": "MIC 5 15",
    "r": [
      "PSA 149 7",
      "ISA 65 12",
      "MIC 5 8",
      "2TH 1 8"
    ]
  },
  {
    "v": "MIC 6 1",
    "r": [
      "DEU 4 26",
      "DEU 32 1",
      "1SA 15 16",
      "PSA 50 1",
      "PSA 50 4",
      "ISA 1 2",
      "ISA 2 12",
      "ISA 3 13",
      "JER 13 15",
      "JER 22 29",
      "EZE 6 3",
      "EZE 36 1",
      "EZE 36 8",
      "EZE 37 4",
      "AMO 3 1",
      "MIC 1 2",
      "MIC 1 4",
      "LUK 19 40",
      "HEB 3 7"
    ]
  },
  {
    "v": "MIC 6 2",
    "r": [
      "DEU 32 22",
      "2SA 22 8",
      "2SA 22 16",
      "PSA 104 5",
      "PRO 8 29",
      "ISA 1 18",
      "ISA 3 13",
      "ISA 5 3",
      "ISA 43 26",
      "JER 2 9",
      "JER 2 29",
      "JER 25 31",
      "JER 31 37",
      "EZE 20 35",
      "HOS 4 1",
      "HOS 12 2",
      "HOS 12 3"
    ]
  },
  {
    "v": "MIC 6 3",
    "r": [
      "PSA 50 7",
      "PSA 51 4",
      "PSA 81 8",
      "PSA 81 13",
      "ISA 43 22",
      "ISA 43 23",
      "JER 2 5",
      "JER 2 31",
      "MIC 6 5",
      "ROM 3 4",
      "ROM 3 19"
    ]
  },
  {
    "v": "MIC 6 4",
    "r": [
      "EXO 4 16",
      "EXO 6 27",
      "EXO 12 51",
      "EXO 14 30",
      "EXO 15 20",
      "EXO 20 2",
      "NUM 12 1",
      "DEU 4 20",
      "DEU 4 34",
      "DEU 5 6",
      "DEU 7 8",
      "DEU 9 26",
      "DEU 15 15",
      "DEU 24 18",
      "2SA 7 23",
      "NEH 9 9",
      "PSA 77 20",
      "PSA 78 51",
      "PSA 106 7",
      "PSA 136 10",
      "ISA 63 9",
      "JER 32 21",
      "EZE 20 5",
      "AMO 2 10",
      "ACT 7 36"
    ]
  },
  {
    "v": "MIC 6 5",
    "r": [
      "NUM 22 1",
      "NUM 22 41",
      "NUM 23 13",
      "NUM 23 27",
      "NUM 25 1",
      "NUM 25 2",
      "NUM 31 8",
      "NUM 31 16",
      "NUM 33 49",
      "DEU 8 2",
      "DEU 8 18",
      "DEU 9 7",
      "DEU 16 3",
      "DEU 23 4",
      "DEU 23 6",
      "JOS 4 19",
      "JOS 5 9",
      "JOS 10 42",
      "JOS 24 9",
      "JOS 24 10",
      "JDG 5 11",
      "1SA 12 7",
      "PSA 36 10",
      "PSA 71 15",
      "PSA 71 19",
      "PSA 103 1",
      "PSA 111 4",
      "PSA 143 11",
      "ROM 3 25",
      "EPH 2 11",
      "2PE 2 15",
      "1JO 1 9",
      "JDE 1 11",
      "REV 2 14"
    ]
  },
  {
    "v": "MIC 6 6",
    "r": [
      "GEN 14 18",
      "EXO 12 5",
      "EXO 23 15",
      "LEV 1 3",
      "NUM 23 1",
      "NUM 23 14",
      "NUM 23 29",
      "2SA 21 3",
      "PSA 22 29",
      "PSA 40 6",
      "PSA 51 16",
      "PSA 95 6",
      "PSA 116 12",
      "PRO 15 8",
      "PRO 21 3",
      "DAN 3 26",
      "DAN 4 9",
      "DAN 5 18",
      "DAN 5 21",
      "MAT 19 16",
      "MAR 5 7",
      "LUK 10 25",
      "JOH 6 26",
      "ACT 2 37",
      "ACT 16 17",
      "ACT 16 30",
      "ROM 10 2",
      "EPH 3 14",
      "HEB 10 4"
    ]
  },
  {
    "v": "MIC 6 7",
    "r": [
      "LEV 18 21",
      "JDG 11 31",
      "JDG 11 39",
      "1SA 15 22",
      "2KI 3 27",
      "2KI 16 3",
      "2KI 21 6",
      "2KI 23 10",
      "JOB 29 6",
      "PSA 10 8",
      "PSA 50 9",
      "PSA 51 16",
      "PSA 51 18",
      "ISA 1 11",
      "ISA 40 16",
      "JER 6 20",
      "JER 7 21",
      "JER 7 31",
      "JER 19 5",
      "EZE 16 20",
      "EZE 23 37",
      "HOS 6 6",
      "AMO 5 22",
      "PHM 1 12"
    ]
  },
  {
    "v": "MIC 6 8",
    "r": [
      "GEN 5 22",
      "GEN 18 19",
      "LEV 26 41",
      "DEU 10 12",
      "DEU 27 10",
      "JOS 24 14",
      "1SA 12 23",
      "1SA 15 22",
      "2CH 30 11",
      "2CH 32 26",
      "2CH 33 12",
      "2CH 33 19",
      "2CH 33 23",
      "2CH 34 27",
      "NEH 9 13",
      "PSA 37 26",
      "PSA 73 28",
      "PSA 101 1",
      "PSA 112 4",
      "PSA 112 9",
      "PRO 21 3",
      "ECC 12 13",
      "ISA 1 16",
      "ISA 57 1",
      "ISA 57 15",
      "ISA 58 6",
      "ISA 66 2",
      "JER 7 3",
      "JER 9 23",
      "JER 22 3",
      "JER 22 16",
      "LAM 3 26",
      "EZE 16 63",
      "DAN 4 37",
      "HOS 6 6",
      "HOS 12 6",
      "AMO 5 24",
      "ZEP 2 3",
      "ZEC 7 9",
      "MAT 3 8",
      "MAT 5 3",
      "MAT 5 7",
      "MAT 18 32",
      "MAR 12 30",
      "LUK 6 36",
      "LUK 10 42",
      "LUK 11 42",
      "LUK 18 13",
      "ROM 7 16",
      "ROM 9 20",
      "ROM 10 1",
      "1CO 7 16",
      "EPH 4 32",
      "COL 3 12",
      "2TH 2 16",
      "TIT 2 11",
      "JAM 2 20",
      "JAM 4 6",
      "1PE 3 8",
      "1PE 5 5",
      "2PE 1 5"
    ]
  },
  {
    "v": "MIC 6 9",
    "r": [
      "EXO 34 5",
      "2SA 21 1",
      "2KI 22 11",
      "JOB 5 6",
      "JOB 5 17",
      "JOB 10 2",
      "JOB 23 14",
      "PSA 9 16",
      "PSA 48 10",
      "PSA 83 18",
      "PSA 107 43",
      "PRO 22 3",
      "ISA 9 13",
      "ISA 10 5",
      "ISA 24 10",
      "ISA 26 11",
      "ISA 27 10",
      "ISA 30 27",
      "ISA 32 13",
      "ISA 40 6",
      "ISA 66 6",
      "JER 14 18",
      "JER 19 11",
      "JER 26 6",
      "JER 26 18",
      "JER 37 8",
      "LAM 3 39",
      "EZE 7 9",
      "HOS 13 16",
      "HOS 14 9",
      "JOE 2 11",
      "AMO 2 5",
      "AMO 3 8",
      "AMO 4 6",
      "AMO 6 1",
      "JON 3 4",
      "MIC 3 12",
      "ZEP 3 2",
      "HAG 1 5",
      "REV 3 19"
    ]
  },
  {
    "v": "MIC 6 10",
    "r": [
      "LEV 19 35",
      "DEU 25 13",
      "DEU 25 16",
      "JOS 7 1",
      "2KI 5 23",
      "PRO 10 2",
      "PRO 11 1",
      "PRO 20 10",
      "PRO 20 23",
      "PRO 21 6",
      "JER 5 26",
      "JER 5 27",
      "EZE 45 9",
      "HOS 12 7",
      "AMO 3 9",
      "AMO 3 10",
      "AMO 8 5",
      "HAB 2 5",
      "ZEP 1 9",
      "ZEC 5 3",
      "ZEC 5 6",
      "JAM 5 1"
    ]
  },
  {
    "v": "MIC 6 11",
    "r": [
      "LEV 19 36",
      "PRO 16 11",
      "PRO 20 10",
      "HOS 12 7"
    ]
  },
  {
    "v": "MIC 6 12",
    "r": [
      "PSA 78 36",
      "PSA 120 2",
      "ISA 1 23",
      "ISA 3 8",
      "ISA 5 7",
      "ISA 59 3",
      "JER 5 5",
      "JER 5 26",
      "JER 6 6",
      "JER 9 2",
      "JER 9 8",
      "EZE 22 6",
      "EZE 22 25",
      "EZE 22 29",
      "HOS 4 1",
      "HOS 7 1",
      "HOS 7 13",
      "AMO 5 11",
      "AMO 6 1",
      "MIC 2 1",
      "MIC 2 2",
      "MIC 3 1",
      "MIC 3 9",
      "MIC 7 2",
      "ZEP 1 9",
      "ZEP 3 3",
      "ACT 24 9",
      "ROM 3 13"
    ]
  },
  {
    "v": "MIC 6 13",
    "r": [
      "LEV 26 16",
      "DEU 28 21",
      "JOB 33 19",
      "PSA 107 17",
      "ISA 1 5",
      "ISA 6 11",
      "JER 14 18",
      "LAM 1 13",
      "LAM 3 11",
      "LAM 5 16",
      "HOS 5 9",
      "HOS 13 16",
      "ACT 12 23"
    ]
  },
  {
    "v": "MIC 6 14",
    "r": [
      "LEV 26 26",
      "DEU 32 22",
      "DEU 32 25",
      "ISA 3 6",
      "ISA 9 20",
      "ISA 24 17",
      "ISA 30 6",
      "ISA 65 13",
      "JER 48 44",
      "EZE 4 16",
      "EZE 5 12",
      "HOS 4 10",
      "AMO 2 14",
      "AMO 9 1",
      "HAG 1 6",
      "HAG 2 16"
    ]
  },
  {
    "v": "MIC 6 15",
    "r": [
      "LEV 26 16",
      "LEV 26 20",
      "DEU 28 38",
      "DEU 28 40",
      "JDG 6 4",
      "ISA 62 8",
      "ISA 65 21",
      "JER 12 13",
      "JOE 1 10",
      "AMO 5 11",
      "ZEP 1 13",
      "HAG 1 6"
    ]
  },
  {
    "v": "MIC 6 16",
    "r": [
      "1KI 9 8",
      "1KI 16 25",
      "1KI 18 4",
      "1KI 21 25",
      "2KI 16 3",
      "2KI 21 3",
      "2CH 22 4",
      "2CH 29 8",
      "2CH 34 25",
      "PSA 1 1",
      "PSA 44 13",
      "PSA 44 14",
      "ISA 9 16",
      "ISA 25 8",
      "JER 7 24",
      "JER 18 15",
      "JER 19 8",
      "JER 21 8",
      "JER 25 9",
      "JER 51 51",
      "LAM 5 1",
      "EZE 8 17",
      "EZE 39 26",
      "DAN 9 16",
      "HOS 5 11",
      "REV 2 20"
    ]
  },
  {
    "v": "MIC 7 1",
    "r": [
      "NUM 18 13",
      "PSA 120 5",
      "PRO 20 6",
      "ISA 6 5",
      "ISA 17 6",
      "ISA 24 13",
      "ISA 24 16",
      "ISA 28 4",
      "JER 4 31",
      "JER 5 1",
      "JER 15 10",
      "JER 45 3",
      "HOS 9 10"
    ]
  },
  {
    "v": "MIC 7 2",
    "r": [
      "1SA 24 11",
      "1SA 26 20",
      "PSA 10 9",
      "PSA 12 1",
      "PSA 12 2",
      "PSA 14 1",
      "PSA 57 6",
      "PRO 1 11",
      "PRO 12 6",
      "ISA 3 5",
      "ISA 57 1",
      "ISA 59 7",
      "JER 5 16",
      "JER 5 26",
      "JER 16 16",
      "LAM 4 18",
      "HOS 6 9",
      "MIC 3 10",
      "HAB 1 15",
      "ACT 24 9",
      "ROM 3 10"
    ]
  },
  {
    "v": "MIC 7 3",
    "r": [
      "1KI 21 9",
      "PRO 4 16",
      "PRO 16 30",
      "ISA 1 23",
      "ISA 26 21",
      "JER 3 5",
      "JER 4 22",
      "JER 8 10",
      "EZE 22 6",
      "EZE 22 27",
      "EZE 34 21",
      "HOS 4 18",
      "AMO 5 12",
      "MIC 3 11",
      "MAT 26 15",
      "LUK 12 1",
      "1CO 4 5"
    ]
  },
  {
    "v": "MIC 7 4",
    "r": [
      "2SA 23 6",
      "ISA 10 3",
      "ISA 22 5",
      "ISA 55 13",
      "JER 8 12",
      "JER 10 15",
      "EZE 2 6",
      "EZE 12 23",
      "HOS 9 7",
      "AMO 8 2",
      "NAH 1 10",
      "LUK 21 25",
      "HEB 6 8"
    ]
  },
  {
    "v": "MIC 7 5",
    "r": [
      "JDG 14 17",
      "JDG 16 5",
      "JOB 6 14",
      "PSA 38 14",
      "PSA 118 8",
      "JER 9 3",
      "JER 9 4",
      "MAT 10 16"
    ]
  },
  {
    "v": "MIC 7 6",
    "r": [
      "GEN 9 22",
      "GEN 49 4",
      "2SA 15 10",
      "2SA 16 11",
      "2SA 16 21",
      "PSA 41 9",
      "PSA 55 12",
      "PRO 30 11",
      "PRO 30 17",
      "ISA 3 5",
      "JER 12 6",
      "JER 20 10",
      "EZE 22 7",
      "OBA 1 7",
      "MAT 10 21",
      "MAT 10 35",
      "MAT 26 23",
      "MAT 26 49",
      "LUK 12 53",
      "LUK 21 16",
      "JOH 13 18",
      "2TI 3 2"
    ]
  },
  {
    "v": "MIC 7 7",
    "r": [
      "GEN 49 18",
      "NUM 5 28",
      "PSA 4 2",
      "PSA 25 5",
      "PSA 27 12",
      "PSA 34 5",
      "PSA 37 7",
      "PSA 38 15",
      "PSA 40 1",
      "PSA 50 15",
      "PSA 55 16",
      "PSA 62 1",
      "PSA 62 6",
      "PSA 65 2",
      "PSA 85 5",
      "PSA 109 4",
      "PSA 130 5",
      "PSA 142 4",
      "ISA 8 17",
      "ISA 12 2",
      "ISA 25 9",
      "ISA 45 22",
      "LAM 3 24",
      "LAM 3 25",
      "HAB 2 3",
      "HAB 3 17",
      "HAB 3 18",
      "LUK 2 25",
      "LUK 6 11",
      "1JO 5 14"
    ]
  },
  {
    "v": "MIC 7 8",
    "r": [
      "JOB 31 29",
      "PSA 13 4",
      "PSA 20 8",
      "PSA 27 1",
      "PSA 35 15",
      "PSA 35 19",
      "PSA 35 24",
      "PSA 37 21",
      "PSA 37 24",
      "PSA 38 16",
      "PSA 41 10",
      "PSA 84 11",
      "PSA 97 11",
      "PSA 107 10",
      "PSA 112 4",
      "PSA 143 3",
      "PRO 24 16",
      "PRO 24 17",
      "ISA 2 5",
      "ISA 9 2",
      "ISA 49 9",
      "ISA 50 10",
      "ISA 60 1",
      "ISA 60 19",
      "JER 50 11",
      "LAM 4 21",
      "EZE 25 6",
      "EZE 35 15",
      "AMO 9 11",
      "OBA 1 12",
      "MIC 7 10",
      "MAL 4 2",
      "MAT 4 16",
      "LUK 1 78",
      "JOH 8 12",
      "JOH 16 20",
      "ACT 26 18",
      "2CO 4 6",
      "REV 11 10",
      "REV 21 23",
      "REV 22 5"
    ]
  },
  {
    "v": "MIC 7 9",
    "r": [
      "LEV 26 41",
      "1SA 3 18",
      "1SA 24 15",
      "1SA 25 39",
      "1SA 26 10",
      "2SA 16 11",
      "2SA 24 17",
      "JOB 23 10",
      "JOB 34 31",
      "JOB 35 14",
      "PSA 7 6",
      "PSA 37 6",
      "PSA 43 1",
      "PSA 119 154",
      "ISA 46 13",
      "ISA 51 22",
      "JER 14 7",
      "JER 50 17",
      "JER 50 33",
      "JER 51 10",
      "JER 51 35",
      "LAM 1 18",
      "LAM 3 39",
      "MAL 3 18",
      "LUK 15 18",
      "1CO 4 5",
      "2TH 1 5",
      "2TI 4 8",
      "HEB 12 6",
      "REV 6 10",
      "REV 18 20"
    ]
  },
  {
    "v": "MIC 7 10",
    "r": [
      "JOS 7 9",
      "2SA 22 43",
      "2KI 9 33",
      "PSA 18 42",
      "PSA 35 26",
      "PSA 42 3",
      "PSA 42 10",
      "PSA 58 10",
      "PSA 79 10",
      "PSA 92 12",
      "PSA 109 29",
      "PSA 115 2",
      "PSA 137 8",
      "ISA 25 10",
      "ISA 26 5",
      "ISA 26 11",
      "ISA 37 10",
      "ISA 41 15",
      "ISA 47 5",
      "ISA 51 22",
      "ISA 63 2",
      "JER 49 15",
      "JER 50 33",
      "JER 51 8",
      "JER 51 24",
      "JER 51 51",
      "EZE 7 18",
      "DAN 3 15",
      "JOE 2 17",
      "OBA 1 10",
      "MIC 4 11",
      "NAH 2 1",
      "ZEP 3 15",
      "ZEC 10 5",
      "MAL 1 5",
      "MAL 4 3",
      "MAT 27 43",
      "REV 17 1",
      "REV 18 20"
    ]
  },
  {
    "v": "MIC 7 11",
    "r": [
      "EZR 4 12",
      "NEH 2 8",
      "NEH 2 17",
      "NEH 3 1",
      "NEH 4 3",
      "NEH 4 6",
      "ISA 54 2",
      "ISA 54 11",
      "ISA 58 12",
      "ISA 61 4",
      "DAN 9 25",
      "AMO 9 11"
    ]
  },
  {
    "v": "MIC 7 12",
    "r": [
      "ISA 11 16",
      "ISA 19 23",
      "ISA 27 12",
      "ISA 43 6",
      "ISA 49 12",
      "ISA 60 4",
      "ISA 66 19",
      "JER 3 18",
      "JER 23 3",
      "JER 31 8",
      "EZE 29 21",
      "EZE 37 21",
      "HOS 11 11"
    ]
  },
  {
    "v": "MIC 7 13",
    "r": [
      "LEV 26 33",
      "JOB 4 8",
      "PRO 1 31",
      "PRO 5 22",
      "PRO 31 31",
      "ISA 3 10",
      "ISA 6 11",
      "ISA 17 9",
      "ISA 24 3",
      "JER 17 10",
      "JER 21 14",
      "JER 25 11",
      "JER 32 19",
      "EZE 12 19",
      "DAN 4 26",
      "MIC 3 12",
      "MIC 6 13",
      "LUK 21 20",
      "GAL 6 7"
    ]
  },
  {
    "v": "MIC 7 14",
    "r": [
      "EXO 33 16",
      "NUM 23 9",
      "NUM 32 1",
      "NUM 32 4",
      "DEU 33 28",
      "PSA 23 1",
      "PSA 28 9",
      "PSA 77 5",
      "PSA 95 7",
      "PSA 100 3",
      "PSA 143 5",
      "ISA 27 13",
      "ISA 35 2",
      "ISA 37 24",
      "ISA 40 11",
      "ISA 49 10",
      "ISA 65 10",
      "JER 50 19",
      "LAM 1 7",
      "LAM 5 21",
      "EZE 34 13",
      "AMO 9 11",
      "OBA 1 19",
      "MIC 5 4",
      "ZEP 3 13",
      "ZEC 10 10",
      "ZEC 11 7",
      "MAL 3 4",
      "MAT 2 6",
      "JOH 10 27",
      "JOH 17 16"
    ]
  },
  {
    "v": "MIC 7 15",
    "r": [
      "EXO 3 20",
      "PSA 68 22",
      "PSA 78 12",
      "ISA 11 16",
      "ISA 51 9",
      "ISA 51 10",
      "ISA 63 11",
      "JER 23 7",
      "JER 23 8"
    ]
  },
  {
    "v": "MIC 7 16",
    "r": [
      "JOB 21 5",
      "JOB 29 9",
      "JOB 40 4",
      "PSA 126 2",
      "ISA 26 11",
      "ISA 52 15",
      "ISA 66 18",
      "EZE 38 23",
      "EZE 39 17",
      "MIC 5 8",
      "ZEC 8 20",
      "ZEC 12 9",
      "ROM 3 19",
      "REV 11 18"
    ]
  },
  {
    "v": "MIC 7 17",
    "r": [
      "GEN 3 14",
      "EXO 15 14",
      "JOS 2 9",
      "JOS 9 24",
      "1SA 14 11",
      "2SA 22 46",
      "2CH 17 10",
      "PSA 9 20",
      "PSA 18 45",
      "PSA 72 9",
      "PSA 72 11",
      "ISA 2 19",
      "ISA 7 19",
      "ISA 25 3",
      "ISA 49 23",
      "ISA 59 19",
      "ISA 60 14",
      "ISA 64 2",
      "ISA 65 25",
      "JER 16 16",
      "JER 33 9",
      "LAM 3 29",
      "ZEC 14 5",
      "REV 3 9",
      "REV 6 15",
      "REV 18 9"
    ]
  },
  {
    "v": "MIC 7 18",
    "r": [
      "EXO 15 11",
      "EXO 33 18",
      "EXO 34 6",
      "EXO 34 9",
      "NUM 14 18",
      "NUM 23 21",
      "DEU 33 26",
      "JDG 10 16",
      "1KI 8 23",
      "NEH 9 17",
      "PSA 35 10",
      "PSA 65 3",
      "PSA 65 4",
      "PSA 71 19",
      "PSA 77 6",
      "PSA 85 4",
      "PSA 86 5",
      "PSA 86 15",
      "PSA 89 6",
      "PSA 89 8",
      "PSA 103 2",
      "PSA 103 8",
      "PSA 103 9",
      "PSA 103 13",
      "PSA 113 5",
      "PSA 130 4",
      "PSA 130 7",
      "ISA 1 18",
      "ISA 38 17",
      "ISA 40 18",
      "ISA 40 25",
      "ISA 43 25",
      "ISA 44 22",
      "ISA 46 8",
      "ISA 55 7",
      "ISA 57 10",
      "ISA 57 16",
      "ISA 62 5",
      "ISA 65 19",
      "JER 3 5",
      "JER 3 12",
      "JER 31 34",
      "JER 32 41",
      "JER 38 8",
      "JER 50 20",
      "LAM 3 31",
      "EZE 33 11",
      "EZE 33 16",
      "DAN 9 9",
      "HOS 14 5",
      "JOE 2 32",
      "AMO 7 8",
      "AMO 8 2",
      "JON 4 2",
      "MIC 2 12",
      "MIC 4 7",
      "MIC 5 3",
      "MIC 5 7",
      "MIC 7 14",
      "ZEP 3 17",
      "LUK 15 5",
      "LUK 15 9",
      "LUK 15 23",
      "LUK 15 32",
      "LUK 24 47",
      "ACT 13 38",
      "ROM 11 4",
      "EPH 2 4",
      "HEB 8 9",
      "JAM 2 13"
    ]
  },
  {
    "v": "MIC 7 19",
    "r": [
      "DEU 30 3",
      "DEU 30 6",
      "DEU 32 36",
      "2SA 24 14",
      "EZR 9 8",
      "PSA 85 3",
      "PSA 90 13",
      "PSA 103 12",
      "PSA 130 8",
      "ISA 33 24",
      "ISA 38 17",
      "ISA 43 25",
      "ISA 63 15",
      "JER 31 20",
      "JER 31 34",
      "JER 50 20",
      "LAM 3 22",
      "LAM 3 32",
      "EZE 11 19",
      "EZE 36 25",
      "EZE 39 29",
      "DAN 9 24",
      "HOS 14 4",
      "ROM 6 14",
      "ROM 6 17",
      "ROM 7 23",
      "ROM 8 2",
      "ROM 8 13",
      "TIT 2 14",
      "JAM 4 5",
      "1JO 3 8"
    ]
  },
  {
    "v": "MIC 7 20",
    "r": [
      "GEN 12 2",
      "GEN 17 7",
      "GEN 22 16",
      "GEN 26 3",
      "GEN 28 13",
      "DEU 7 8",
      "PSA 105 8",
      "JER 33 6",
      "JER 33 25",
      "LUK 1 54",
      "LUK 1 72",
      "ACT 3 25",
      "ROM 11 26",
      "HEB 6 13"
    ]
  }
]